LICENSE
libcnb/__init__.py
libcnb/_build.py
libcnb/_buildpack.py
libcnb/_detect.py
libcnb/_layers.py
libcnb/_output.py
libcnb/_plan.py
libcnb/_platform.py
libcnb/_run.py
libcnb/py.typed
libcnb-0.2.2.dist-info/LICENSE
libcnb-0.2.2.dist-info/WHEEL
libcnb-0.2.2.dist-info/METADATA
libcnb-0.2.2.dist-info/RECORD
