Metadata-Version: 2.1
Name: libcnb
Version: 0.2.2
Summary:  Cloud Native Buildpack API bindings for Python
Home-page: https://github.com/samj1912/python-libcnb
License: Apache-2.0
Author: Sambhav Kothari
Author-email: sambhavs.email@gmail.com
Requires-Python: >=3.7,<4.0
Classifier: License :: OSI Approved :: Apache Software License
Classifier: Natural Language :: English
Classifier: Programming Language :: Python :: 3
Classifier: Programming Language :: Python :: 3.7
Classifier: Programming Language :: Python :: 3.8
Classifier: Programming Language :: Python :: 3.9
Requires-Dist: importlib_metadata (>=3.4.0,<4.0.0)
Requires-Dist: packaging (>=20.9,<21.0)
Requires-Dist: pydantic (>=1.8.1,<2.0.0)
Requires-Dist: toml (>=0.10.2,<0.11.0)
